LICENSE
MANIFEST.in
README.md
setup.py
surfaicedbms/__init__.py
surfaicedbms/dataProcessor.py
surfaicedbms/edgeApp.py
surfaicedbms/mongoTransactions.py
surfaicedbms/nxOperations.py
surfaicedbms/qualityApp.py
surfaicedbms/tsdbTransactions.py
surfaicedbms.egg-info/PKG-INFO
surfaicedbms.egg-info/SOURCES.txt
surfaicedbms.egg-info/dependency_links.txt
surfaicedbms.egg-info/requires.txt
surfaicedbms.egg-info/top_level.txt
surfaicedbms/build/__init__.py
surfaicedbms/build/buildRelationalDb.py
surfaicedbms/build/destructRelationalDb.py
surfaicedbms/data/config.yaml
surfaicedbms/data/inputs/camSetup/2022_6_14_11_40_pless.prt
surfaicedbms/data/inputs/mockFiles/15th_experiment/1681457243.899068.csv
surfaicedbms/data/inputs/mockFiles/15th_experiment/1681457381.719391.csv
surfaicedbms/data/inputs/mockFiles/15th_experiment/1681457540.697088.csv
surfaicedbms/data/inputs/mockFiles/15th_experiment/Acc_1681457006.csv
surfaicedbms/data/inputs/mockFiles/15th_experiment/Acc_1681457254.csv
surfaicedbms/data/inputs/mockFiles/15th_experiment/Acc_1681457386.csv
surfaicedbms/data/outputs/3dPdf/3D_2022_6_14_11_40_pless.pdf
surfaicedbms/data/outputs/formedProfiles/merged_data.csv
surfaicedbms/data/outputs/logger/logger.log
surfaicedbms/data/outputs/manufacturing_operations_metadata/manopt_output.csv.gz
surfaicedbms/data/outputs/processed_manufacturing_data/acc_output.csv.gz
surfaicedbms/data/outputs/processed_manufacturing_data/nc_output.csv.gz
surfaicedbms/data/outputs/rarz/rarz_output.csv.gz
surfaicedbms/data/outputs/workpieceOutput/G_CODE.ptp
surfaicedbms/data_analysis/__init__.py
surfaicedbms/data_analysis/surfaiceQueries.py
surfaicedbms/data_feed/__init__.py
surfaicedbms/data_feed/planningMain.py
surfaicedbms/data_feed/planningMain_db4mr.py
surfaicedbms/data_feed/planningMain_json.py
surfaicedbms/data_feed/processMain.py
surfaicedbms/data_feed/qualityMain.py