Metadata-Version: 2.1
Name: surfaicedbms
Version: 0.6.0
Summary: Surfaicedbms PyPi Version
Home-page: https://git.ift.tuwien.ac.at/lab/ift/sis/projects/surfaice/surfaice-dbms
Author: Atahan Kap
Author-email: atahan.kap@student.tuwien.ac.at
Classifier: Programming Language :: Python :: 3
Classifier: License :: OSI Approved :: MIT License
Classifier: Operating System :: OS Independent
Requires-Python: >=3.10
License-File: LICENSE
